semiauto_clustering/__init__.py
semiauto_clustering/custom_transformers.py
semiauto_clustering/utils.py
semiauto_clustering/data/__init__.py
semiauto_clustering/data/data_cleaning.py
semiauto_clustering/data/data_ingestion.py
semiauto_clustering/data/data_preprocessing.py
semiauto_clustering/features/__init__.py
semiauto_clustering/features/feature_engineering.py
semiauto_clustering/logger/__init__.py
semiauto_clustering/models/__init__.py
semiauto_clustering/models/model_building.py
semiauto_clustering/models/model_evaluation.py
semiauto_clustering/models/model_optimization.py
semiauto_clustering/visualization/__init__.py
semiauto_clustering/visualization/projectflow_report.py
semiauto_clustering-1.0.3.dist-info/licenses/LICENSE
semiauto_clustering-1.0.3.dist-info/METADATA
semiauto_clustering-1.0.3.dist-info/WHEEL
semiauto_clustering-1.0.3.dist-info/entry_points.txt
semiauto_clustering-1.0.3.dist-info/top_level.txt
semiauto_clustering-1.0.3.dist-info/RECORD
