Metadata-Version: 2.4
Name: semiauto-clustering
Version: 1.0.3
Summary: Automated clustering pipeline for machine learning
Home-page: https://github.com/Akshat-Sharma-110011/SemiAuto-Clustring
Author: Akshat-Sharma-110011
Author-email: akshatsharma.business.1310@gmail.com
Classifier: Programming Language :: Python :: 3
Classifier: License :: OSI Approved :: MIT License
Classifier: Operating System :: OS Independent
Requires-Python: >=3.8
License-File: LICENSE
Requires-Dist: numpy<1.26.0,>=1.21.0
Requires-Dist: pandas
Requires-Dist: scikit-learn
Requires-Dist: scipy
Requires-Dist: PyYAML
Requires-Dist: cloudpickle
Requires-Dist: fastapi
Requires-Dist: uvicorn
Requires-Dist: matplotlib
Requires-Dist: seaborn
Requires-Dist: optuna
Requires-Dist: hdbscan
Dynamic: author
Dynamic: author-email
Dynamic: classifier
Dynamic: description
Dynamic: description-content-type
Dynamic: home-page
Dynamic: license-file
Dynamic: requires-dist
Dynamic: requires-python
Dynamic: summary
